[
  {
    "Name": "count",
    "IsPublic": true,
    "Aliases": [
      "count"
    ],
    "Scope": "Array",
    "Summary": "Counts the number of accumulated items, including  values.",
    "Parameters": []
  },
  {
    "Name": "sum",
    "IsPublic": true,
    "Aliases": [
      "sum"
    ],
    "Scope": "Array",
    "Summary": "Computes the sum of all accumulated numeric values.",
    "Parameters": []
  },
  {
    "Name": "min",
    "IsPublic": true,
    "Aliases": [
      "min"
    ],
    "Scope": "Array",
    "Summary": "Tracks the smallest numeric value found during accumulation.",
    "Parameters": []
  },
  {
    "Name": "max",
    "IsPublic": true,
    "Aliases": [
      "max"
    ],
    "Scope": "Array",
    "Summary": "Tracks the greatest numeric value found during accumulation.",
    "Parameters": []
  },
  {
    "Name": "first",
    "IsPublic": true,
    "Aliases": [
      "first"
    ],
    "Scope": "Array",
    "Summary": "Stores the first accumulated item and ignores all subsequent items.",
    "Parameters": []
  },
  {
    "Name": "last",
    "IsPublic": true,
    "Aliases": [
      "last"
    ],
    "Scope": "Array",
    "Summary": "Stores the most recently accumulated item.",
    "Parameters": []
  }
]
